inputconditioner.v
//------------------------------------------------------------------------
// Input Conditioner
//    1) Synchronizes input to clock domain
//    2) Debounces input
//    3) Creates pulses at edge transitions
//------------------------------------------------------------------------

module inputconditioner
(
input 	    clk,            // Clock domain to synchronize input to
input	    noisysignal,    // (Potentially) noisy input signal
output reg  conditioned,    // Conditioned output signal
output reg  positiveedge,   // 1 clk pulse at rising edge of conditioned
output reg  negativeedge    // 1 clk pulse at falling edge of conditioned
);

    parameter counterwidth = 3; // Counter size, in bits, >= log2(waittime)
    parameter waittime = 5;     // Debounce delay, in clock cycles
    
    reg[counterwidth-1:0] counter = 0; // 0
    reg synchronizer0 = 0; // 1
    reg synchronizer1 = 0; // 1
    // conditioned <= 0;
    
    // 0 0 0 0 1 0 1 1 1 1 1 
    always @(posedge clk ) begin
        if(conditioned == synchronizer1)
            counter <= 0;
        else begin
            if( counter == waittime) begin
                counter <= 0;
                conditioned <= synchronizer1;
            end
            else 
                counter <= counter+1;
        end
        synchronizer0 <= noisysignal;
        synchronizer1 <= synchronizer0;
    end
endmodule

inputconditioner.t.v
//------------------------------------------------------------------------
// Input Conditioner test bench
//------------------------------------------------------------------------
`include "inputconditioner.v"

module testConditioner();

    reg clk;
    reg pin;
    wire conditioned;
    wire rising;
    wire falling;
    
    inputconditioner dut(.clk(clk),
    			 .noisysignal(pin),
			 .conditioned(conditioned),
			 .positiveedge(rising),
			 .negativeedge(falling));


    // Generate clock (50MHz)
    initial clk=0;
    always #10 clk=!clk;    // 50MHz Clock
    
    initial begin
        $dumpfile("inputconditioner.vcd");
        $dumpvars;
        pin=0; #10
        pin=0; #10
        pin=0; #10
        pin=0; #10
        pin=1; #10
        pin=0; #10
        pin=1; #10
        pin=1; #10
        pin=1; #10
        pin=1; #10
        pin=1; #10
        pin=1; #10
        pin=0; #10
        pin=0; #10
        pin=0; #10
        pin=0; #10
        pin=0; #10
        pin=0; #10
        pin=0; #10
        pin=0; #10
        pin=0; #10
        pin=0; #10
        pin=0; #10
        pin=0; #10
        pin=0; #10
        pin=0; #10
        pin=0; #10
        pin=0; #10
        $finish;
    end

    // Your Test Code
    // Be sure to test each of the three conditioner functions:
    // Synchronization, Debouncing, Edge Detection
    
endmodule

inputconditioner.vcd
$date
	Tue Oct 24 16:41:04 2017
$end
$version
	Icarus Verilog
$end
$timescale
	1s
$end
$scope module testConditioner $end
$var wire 1 ! conditioned $end
$var wire 1 " falling $end
$var wire 1 # rising $end
$var reg 1 $ clk $end
$var reg 1 % pin $end
$scope module dut $end
$var wire 1 & clk $end
$var wire 1 ' noisysignal $end
$var reg 1 ( conditioned $end
$var reg 3 ) counter [2:0] $end
$var reg 1 * negativeedge $end
$var reg 1 + positiveedge $end
$var reg 1 , synchronizer0 $end
$var reg 1 - synchronizer1 $end
$upscope $end
$upscope $end
$enddefinitions $end
#0
$dumpvars
0-
0,
x+
x*
b0 )
x(
0'
0&
0%
0$
x#
x"
x!
$end
#10
b1 )
1$
1&
#20
0$
0&
#30
b10 )
1$
1&
#40
1%
1'
0$
0&
#50
b11 )
0%
0'
1$
1&
#60
1%
1'
0$
0&
#70
1,
b100 )
1$
1&
#80
0$
0&
#90
1-
b101 )
1$
1&
#100
0$
0&
#110
1(
1!
b0 )
1$
1&
#120
0%
0'
0$
0&
#130
0,
1$
1&
#140
0$
0&
#150
0-
1$
1&
#160
0$
0&
#170
b1 )
1$
1&
#180
0$
0&
#190
b10 )
1$
1&
#200
0$
0&
#210
b11 )
1$
1&
#220
0$
0&
#230
b100 )
1$
1&
#240
0$
0&
#250
b101 )
1$
1&
#260
0$
0&
#270
0(
0!
b0 )
1$
1&
