inputconditioner.v
//------------------------------------------------------------------------
// Input Conditioner
//    1) Synchronizes input to clock domain
//    2) Debounces input
//    3) Creates pulses at edge transitions
//------------------------------------------------------------------------

module inputconditioner
(
input 	    clk,            // Clock domain to synchronize input to
input	    noisysignal,    // (Potentially) noisy input signal
output wire conditioned,    // Conditioned output signal
output reg  positiveedge,   // 1 clk pulse at rising edge of conditioned
output reg  negativeedge    // 1 clk pulse at falling edge of conditioned
);
    debouncer deb(clk, noisysignal, conditioned);

    reg prevconditioned = 0;
    always @(posedge clk ) begin

        // look for positive edge
        if((conditioned == 1) & (prevconditioned == 0)) begin
            positiveedge <= 1;
        end
        else begin
            positiveedge <= 0;
        end

        // look for negative edge
        if ((conditioned == 0) & (prevconditioned == 1)) begin
            negativeedge <= 1;
        end
        else begin
            negativeedge <= 0;
        end
        prevconditioned <= conditioned;
    end
endmodule

// only changes the input signal after it is stable for a given wait_time
module debouncer
(
input       clk,   // Clock domain to synchronize input to
input       sig,   // (Potentially) noisy input signal
output reg  out    // Debounced output signal
);
    parameter wait_time = 3;     // Debounce delay, in clock cycles

    reg[wait_time-1:0] prev_vals;
    //0 0 0 0 1 0 1 1 1 1
    always @(posedge clk ) begin
        // Case 1: The previous values are all 1s
        if( prev_vals == ((2**wait_time) - 1)) begin
            out <= 1;
        end
        // Case 2: The previous values are all 0s
        else if( prev_vals == 0) begin
            out <= 0;
        end
        // Update the previous values to have the new signal bit
        // Note that the output won't reflect the latest signal
        // until the next clock cycle
        prev_vals <= {prev_vals, sig}; // wont this overflow? when are we deleting from prev_vals?
    end
endmodule

inputconditioner.t.v
//------------------------------------------------------------------------
// Input Conditioner test bench
//------------------------------------------------------------------------
`include "inputconditioner.v"

module testConditioner();

    reg clk;
    reg pin;
    wire conditioned;
    wire rising;
    wire falling;

    inputconditioner dut(.clk(clk),
    			 .noisysignal(pin),
			 .conditioned(conditioned),
			 .positiveedge(rising),
			 .negativeedge(falling));


    // Generate clock (50MHz)
    initial clk=0;
    always #5 clk=!clk;    // 50MHz Clock

    initial begin
        $dumpfile("inputconditioner.vcd");
        $dumpvars;
        // Initialize conditioner by running at 0 for 3 clock cycles
        pin=0; #40

        pin=1; #10
        pin=0; #10
        pin=1; #80
        pin=0; #100
        pin=1; #10
        pin=0; #10
        pin=1; #10
        pin=0; #10
        pin=1; #80
        pin=0;
        #100
        $finish;
    end

    // Your Test Code
    // Be sure to test each of the three conditioner functions:
    // Synchronization, Debouncing, Edge Detection

endmodule

inputconditioner.vcd
$date
	Wed Oct 25 12:57:12 2017
$end
$version
	Icarus Verilog
$end
$timescale
	1s
$end
$scope module testConditioner $end
$var wire 1 ! conditioned $end
$var wire 1 " falling $end
$var wire 1 # rising $end
$var reg 1 $ clk $end
$var reg 1 % pin $end
$scope module dut $end
$var wire 1 & clk $end
$var wire 1 ! conditioned $end
$var wire 1 ' noisysignal $end
$var reg 1 ( negativeedge $end
$var reg 1 ) positiveedge $end
$var reg 1 * prevconditioned $end
$scope module deb $end
$var wire 1 & clk $end
$var wire 1 ' sig $end
$var reg 1 + out $end
$var reg 3 , prev_vals [2:0] $end
$upscope $end
$upscope $end
$upscope $end
$enddefinitions $end
#0
$dumpvars
bx ,
x+
0*
x)
x(
0'
0&
0%
0$
x#
x"
x!
$end
#5
bx0 ,
x*
0(
0"
0)
0#
1$
1&
#10
0$
0&
#15
bx00 ,
1$
1&
#20
0$
0&
#25
b0 ,
1$
1&
#30
0$
0&
#35
0+
0!
1$
1&
#40
0$
0&
1%
1'
#45
b1 ,
0*
1$
1&
#50
0$
0&
0%
0'
#55
b10 ,
1$
1&
#60
0$
0&
1%
1'
#65
b101 ,
1$
1&
#70
0$
0&
#75
b11 ,
1$
1&
#80
0$
0&
#85
b111 ,
1$
1&
#90
0$
0&
#95
1+
1!
1$
1&
#100
0$
0&
#105
1*
1)
1#
1$
1&
#110
0$
0&
#115
0)
0#
1$
1&
#120
0$
0&
#125
1$
1&
#130
0$
0&
#135
1$
1&
#140
0$
0&
0%
0'
#145
b110 ,
1$
1&
#150
0$
0&
#155
b100 ,
1$
1&
#160
0$
0&
#165
b0 ,
1$
1&
#170
0$
0&
#175
0+
0!
1$
1&
#180
0$
0&
#185
0*
1(
1"
1$
1&
#190
0$
0&
#195
0(
0"
1$
1&
#200
0$
0&
#205
1$
1&
#210
0$
0&
#215
1$
1&
#220
0$
0&
#225
1$
1&
#230
0$
0&
#235
1$
1&
#240
0$
0&
1%
1'
#245
b1 ,
1$
1&
#250
0$
0&
0%
0'
#255
b10 ,
1$
1&
#260
0$
0&
1%
1'
#265
b101 ,
1$
1&
#270
0$
0&
0%
0'
#275
b10 ,
1$
1&
#280
0$
0&
1%
1'
#285
b101 ,
1$
1&
#290
0$
0&
#295
b11 ,
1$
1&
#300
0$
0&
#305
b111 ,
1$
1&
#310
0$
0&
#315
1+
1!
1$
1&
#320
0$
0&
#325
1*
1)
1#
1$
1&
#330
0$
0&
#335
0)
0#
1$
1&
#340
0$
0&
#345
1$
1&
#350
0$
0&
#355
1$
1&
#360
0$
0&
0%
0'
#365
b110 ,
1$
1&
#370
0$
0&
#375
b100 ,
1$
1&
#380
0$
0&
#385
b0 ,
1$
1&
#390
0$
0&
#395
0+
0!
1$
1&
#400
0$
0&
#405
0*
1(
1"
1$
1&
#410
0$
0&
#415
0(
0"
1$
1&
