inputconditioner.v
//------------------------------------------------------------------------
// Input Conditioner
//    1) Synchronizes input to clock domain
//    2) Debounces input
//    3) Creates pulses at edge transitions
//------------------------------------------------------------------------

module inputconditioner
(
input 	    clk,            // Clock domain to synchronize input to
input	    noisysignal,    // (Potentially) noisy input signal
output reg  conditioned,    // Conditioned output signal
output reg  positiveedge,   // 1 clk pulse at rising edge of conditioned
output reg  negativeedge    // 1 clk pulse at falling edge of conditioned
);

    parameter counterwidth = 3; // Counter size, in bits, >= log2(waittime)
    parameter waittime = 3;     // Debounce delay, in clock cycles
    
    reg[counterwidth-1:0] counter = 0;
    reg synchronizer0 = 0;
    reg synchronizer1 = 0;
    
    always @(posedge clk ) begin
        if(conditioned == synchronizer1) begin
            counter <= 0;
            positiveedge <= 0;
            negativeedge <= 0;
        end
        else begin
            if( counter == waittime) begin
                counter <= 0;
                conditioned <= synchronizer1;
                if (synchronizer1 == 1) begin
                    positiveedge <= 1;
                end
                else begin
                    negativeedge <= 1;
                end
            end
            else 
                counter <= counter+1;
        end
        synchronizer0 <= noisysignal;
        synchronizer1 <= synchronizer0;
    end
endmodule

inputconditioner.t.v
//------------------------------------------------------------------------
// Input Conditioner test bench
//------------------------------------------------------------------------
`include "inputconditioner.v"

module testConditioner();


    reg clk;
    reg pin;
    wire conditioned;
    wire rising;
    wire falling;
    
    inputconditioner dut(.clk(clk),
    			 .noisysignal(pin),
			 .conditioned(conditioned),
			 .positiveedge(rising),
			 .negativeedge(falling)); 

    initial clk=0;
    always #10 clk=!clk;    // 50MHz Clock  
    initial begin

$dumpfile("inputconditioner.vcd");
$dumpvars();

$display(" clk | pin | conditioned | -edge| + edge"); 
pin = 0; #50
$display("%b | %b | %b | %b | %b", clk, pin, conditioned, rising, falling );
pin = 1; #80
$display("%b | %b | %b | %b | %b", clk, pin, conditioned, rising, falling );
pin = 0; #12
$display("%b | %b | %b | %b | %b", clk, pin, conditioned, rising, falling );
pin = 1; #70
$display("%b | %b | %b | %b | %b", clk, pin, conditioned, rising, falling );
pin = 0; #90
$display("%b | %b | %b | %b | %b", clk, pin, conditioned, rising, falling );
pin = 1; #8
$display("%b | %b | %b | %b | %b", clk, pin, conditioned, rising, falling );
pin = 0; #70
$display("%b | %b | %b | %b | %b", clk, pin, conditioned, rising, falling );
pin = 1; #150
$display("%b | %b | %b | %b | %b", clk, pin, conditioned, rising, falling );
pin = 0; #50
$display("%b | %b | %b | %b | %b", clk, pin, conditioned, rising, falling );
pin = 1; #15
$display("%b | %b | %b | %b | %b", clk, pin, conditioned, rising, falling );
pin = 0; #1
$display("%b | %b | %b | %b | %b", clk, pin, conditioned, rising, falling );
pin = 1; #70
$display("%b | %b | %b | %b | %b", clk, pin, conditioned, rising, falling );
pin = 0; #50
$display("%b | %b | %b | %b | %b", clk, pin, conditioned, rising, falling );
pin = 1; #5
$display("%b | %b | %b | %b | %b", clk, pin, conditioned, rising, falling );
pin = 0; #280
$display("%b | %b | %b | %b | %b", clk, pin, conditioned, rising, falling );

// something shiesty is going on with the passing from synchronizer 1 to the conditioned signal.
// I'll try to take a look at it again before we meet. 
// See GTK wave simulation with these paramters to observe jankness with your own eyes. 
/*
pin = 0; #50
pin = 1; #160
pin = 0; #70
pin = 1; #10
pin = 0; #80

pin = 1; #60
pin = 0; #100
pin = 1; #65
pin = 0; #100
pin = 1; #70

pin = 0; #150
*/
// pin = 1; #50
// pin = 0; #15
// pin = 1; #1
// pin = 0; #70
// pin = 1; #50



$finish; 
end

endmodule

inputconditioner.vcd
$date
	Mon Oct 23 19:58:44 2017
$end
$version
	Icarus Verilog
$end
$timescale
	1s
$end
$scope module testConditioner $end
$var wire 1 ! conditioned $end
$var wire 1 " falling $end
$var wire 1 # rising $end
$var reg 1 $ clk $end
$var reg 1 % pin $end
$scope module dut $end
$var wire 1 & clk $end
$var wire 1 ' noisysignal $end
$var reg 1 ( conditioned $end
$var reg 3 ) counter [2:0] $end
$var reg 1 * negativeedge $end
$var reg 1 + positiveedge $end
$var reg 1 , synchronizer0 $end
$var reg 1 - synchronizer1 $end
$upscope $end
$upscope $end
$enddefinitions $end
#0
$dumpvars
0-
0,
x+
x*
b0 )
x(
0'
0&
0%
0$
x#
x"
x!
$end
#10
b1 )
1$
1&
#20
0$
0&
#30
b10 )
1$
1&
#40
0$
0&
#50
1,
b11 )
1$
1&
1%
1'
#60
0$
0&
#70
1-
0(
0!
b0 )
1$
1&
#80
0$
0&
#90
b1 )
1$
1&
#100
0$
0&
#110
b10 )
1$
1&
#120
0$
0&
#130
0,
b11 )
1$
1&
0%
0'
#140
0$
0&
#142
1%
1'
#150
0-
1,
1+
1#
1(
1!
b0 )
1$
1&
#160
0$
0&
#170
1-
0+
0#
b1 )
1$
1&
#180
0$
0&
#190
b0 )
1$
1&
#200
0$
0&
#210
1$
1&
#212
0%
0'
#220
0$
0&
#230
0,
1$
1&
#240
0$
0&
#250
0-
1$
1&
#260
0$
0&
#270
b1 )
1$
1&
#280
0$
0&
#290
b10 )
1$
1&
#300
0$
0&
#302
1%
1'
#310
b11 )
0%
0'
1$
1&
#320
0$
0&
#330
1*
1"
0(
0!
b0 )
1$
1&
#340
0$
0&
#350
0*
0"
1$
1&
#360
0$
0&
#370
1$
1&
#380
0$
0&
1%
1'
#390
1,
1$
1&
#400
0$
0&
#410
1-
1$
1&
#420
0$
0&
#430
b1 )
1$
1&
#440
0$
0&
#450
b10 )
1$
1&
#460
0$
0&
#470
b11 )
1$
1&
#480
0$
0&
#490
1+
1#
1(
1!
b0 )
1$
1&
#500
0$
0&
#510
0+
0#
1$
1&
#520
0$
0&
#530
0,
1$
1&
0%
0'
#540
0$
0&
#550
0-
1$
1&
#560
0$
0&
#570
b1 )
1$
1&
#580
0$
0&
1%
1'
#590
1,
b10 )
1$
1&
#595
0%
0'
#596
1%
1'
#600
0$
0&
#610
1-
b11 )
1$
1&
#620
0$
0&
#630
b0 )
1$
1&
#640
0$
0&
#650
1$
1&
#660
0$
0&
#666
0%
0'
#670
0,
1$
1&
#680
0$
0&
#690
0-
1$
1&
#700
0$
0&
#710
b1 )
1$
1&
#716
1%
1'
#720
0$
0&
#721
0%
0'
#730
b10 )
1$
1&
#740
0$
0&
#750
b11 )
1$
1&
#760
0$
0&
#770
1*
1"
0(
0!
b0 )
1$
1&
#780
0$
0&
#790
0*
0"
1$
1&
