inputconditioner.v
//------------------------------------------------------------------------
// Input Conditioner
//    1) Synchronizes input to clock domain
//    2) Debounces input
//    3) Creates pulses at edge transitions
//------------------------------------------------------------------------

module inputconditioner
(
input 	    clk,            // Clock domain to synchronize input to
input	    noisysignal,    // (Potentially) noisy input signal
output reg  conditioned,    // Conditioned output signal
output reg  positiveedge,   // 1 clk pulse at rising edge of conditioned
output reg  negativeedge    // 1 clk pulse at falling edge of conditioned
);

    parameter counterwidth = 3; // Counter size, in bits, >= log2(waittime)
    parameter waittime = 3;     // Debounce delay, in clock cycles
    
    reg[counterwidth-1:0] counter = 0;
    reg synchronizer0 = 0;
    reg synchronizer1 = 0;
    
    always @(posedge clk ) begin
        if(conditioned == synchronizer1) begin
            counter <= 0;
            positiveedge <= 0;
            negativeedge <= 0;
        end
        else begin
            if( counter == waittime) begin
                counter <= 0;
                conditioned <= synchronizer1;
                if (synchronizer1 == 1) begin
                    positiveedge <= 1;
                end
                else begin
                    negativeedge <= 1;
                end
            end
            else 
                counter <= counter+1;
        end
        synchronizer0 <= noisysignal;
        synchronizer1 <= synchronizer0;
    end
endmodule

inputconditioner.t.v
//------------------------------------------------------------------------
// Input Conditioner test bench
//------------------------------------------------------------------------
`include "inputconditioner.v"

module testConditioner();

    reg clk;
    reg pin;
    wire conditioned;
    wire rising;
    wire falling;

    inputconditioner dut(.clk(clk),
    			 .noisysignal(pin),
			 .conditioned(conditioned),
			 .positiveedge(rising),
			 .negativeedge(falling));


    // Generate clock (50MHz)
    initial clk=0;
    always #5 clk=!clk;    // 50MHz Clock

    initial begin
        $dumpfile("inputconditioner.vcd");
        $dumpvars;
        // Initialize conditioner by running at 0 for 3 clock cycles
        pin=0; #40

        pin=1; #10
        pin=0; #10
        pin=1; #80
        pin=0; #100
        pin=1; #10
        pin=0; #10
        pin=1; #10
        pin=0; #10
        pin=1; #80
        pin=0;
        #100
        $finish;
    end

    // Your Test Code
    // Be sure to test each of the three conditioner functions:
    // Synchronization, Debouncing, Edge Detection

endmodule

inputconditioner.vcd
$date
	Sun Oct 22 15:36:43 2017
$end
$version
	Icarus Verilog
$end
$timescale
	1s
$end
$scope module testConditioner $end
$var wire 1 ! conditioned $end
$var wire 1 " falling $end
$var wire 1 # rising $end
$var reg 1 $ clk $end
$var reg 1 % pin $end
$scope module dut $end
$var wire 1 & clk $end
$var wire 1 ' noisysignal $end
$var reg 1 ( conditioned $end
$var reg 3 ) counter [2:0] $end
$var reg 1 * negativeedge $end
$var reg 1 + positiveedge $end
$var reg 1 , synchronizer0 $end
$var reg 1 - synchronizer1 $end
$upscope $end
$upscope $end
$enddefinitions $end
#0
$dumpvars
0-
0,
x+
x*
b0 )
x(
0'
0&
0%
0$
x#
x"
x!
$end
#10
b1 )
1$
1&
#20
0$
0&
#30
b10 )
1$
1&
#40
0$
0&
#50
b11 )
1$
1&
#60
0$
0&
#70
0(
0!
b0 )
1$
1&
#80
0$
0&
#90
1$
1&
#100
0$
0&
#110
1$
1&
#120
0$
0&
#130
1$
1&
#140
0$
0&
#150
1$
1&
#160
0$
0&
#170
1$
1&
#180
0$
0&
#190
1$
1&
#200
0$
0&
#210
1$
1&
#220
0$
0&
#230
1$
1&
#240
0$
0&
#250
1$
1&
#260
0$
0&
#270
1$
1&
#280
0$
0&
#290
1$
1&
#300
0$
0&
#310
1$
1&
#320
0$
0&
#330
1$
1&
#340
0$
0&
#350
1$
1&
#360
0$
0&
#370
1$
1&
#380
0$
0&
#390
1$
1&
#400
0$
0&
1%
1'
#410
1,
1$
1&
#420
0$
0&
#430
1-
1$
1&
#440
0$
0&
#450
b1 )
1$
1&
#460
0$
0&
#470
b10 )
1$
1&
#480
0$
0&
#490
b11 )
1$
1&
#500
0$
0&
0%
0'
#502
1%
1'
#510
1+
1#
1(
1!
b0 )
1$
1&
#520
0$
0&
#530
0+
0#
1$
1&
#540
0$
0&
#550
1$
1&
#560
0$
0&
#570
1$
1&
#580
0$
0&
#590
1$
1&
#600
0$
0&
#602
0%
0'
#610
0,
1$
1&
#620
0$
0&
#630
0-
1$
1&
#640
0$
0&
#650
b1 )
1$
1&
#660
0$
0&
#670
b10 )
1$
1&
#680
0$
0&
#690
b11 )
1$
1&
#700
0$
0&
#710
1*
1"
0(
0!
b0 )
1$
1&
#720
0$
0&
#730
0*
0"
1$
1&
#740
0$
0&
#750
1$
1&
#760
0$
0&
#770
1$
1&
#780
0$
0&
#790
1$
1&
#800
0$
0&
#810
1$
1&
#820
0$
0&
#830
1$
1&
#840
0$
0&
#850
1$
1&
#860
0$
0&
#870
1$
1&
#880
0$
0&
#890
1$
1&
#900
0$
0&
#902
1%
1'
#905
0%
0'
#910
1$
1&
#920
0$
0&
#930
1$
1&
#940
0$
0&
#950
1$
1&
#960
0$
0&
#970
1$
1&
#980
0$
0&
#990
1$
1&
#1000
0$
0&
#1005
1%
1'
#1010
1,
1$
1&
#1020
0$
0&
#1030
1-
1$
1&
#1040
0$
0&
#1050
b1 )
1$
1&
#1060
0$
0&
#1070
b10 )
1$
1&
#1080
0$
0&
#1090
b11 )
1$
1&
#1100
0$
0&
#1110
1+
1#
1(
1!
b0 )
1$
1&
#1120
0$
0&
#1130
0+
0#
1$
1&
