inputconditioner.v
//------------------------------------------------------------------------
// Input Conditioner
//    1) Synchronizes input to clock domain
//    2) Debounces input
//    3) Creates pulses at edge transitions
//------------------------------------------------------------------------

module inputconditioner
(
input 	    clk,            // Clock domain to synchronize input to
input	    noisysignal,    // (Potentially) noisy input signal
output wire conditioned,    // Conditioned output signal
output reg  positiveedge,   // 1 clk pulse at rising edge of conditioned
output reg  negativeedge    // 1 clk pulse at falling edge of conditioned
);
    debouncer deb(clk, noisysignal, conditioned);

    reg prevconditioned = 0;
    always @(posedge clk ) begin
        if(conditioned == 0 & prevconditioned == 1) begin
            positiveedge <= 1;
        end
        else begin
            negativeedge <= 0;
        end
    end
endmodule

// only changes the input signal after it is stable for a given waittime
module debouncer
(
input       clk,   // Clock domain to synchronize input to
input       sig,   // (Potentially) noisy input signal
output reg  out    // Debounced output signal
);

    parameter counterwidth = 3; // Counter size, in bits, >= log2(waittime)
    parameter waittime = 2;     // Debounce delay, in clock cycles

    reg[counterwidth-1:0] counter = 0;
    reg synchronizer0 = 0;
    reg synchronizer1 = 0;

    //0 0 0 0 1 0 1 1 1 1
    always @(posedge clk ) begin
        // Case 1: previous signal is same as current output
        if(out == synchronizer1)
            counter <= 0;
        else begin
            // Case 2: Counter reaches maximum limit
            if( counter == waittime) begin
                counter <= 0;
                out <= synchronizer1;
            end
            // Case 3: Counter has not reached max limit
            else
                counter <= counter+1;
        end
        synchronizer0 <= sig;
        synchronizer1 <= synchronizer0;
    end
endmodule

inputconditioner.t.v
//------------------------------------------------------------------------
// Input Conditioner test bench
//------------------------------------------------------------------------
`include "inputconditioner.v"

module testConditioner();

    reg clk;
    reg pin;
    wire conditioned;
    wire rising;
    wire falling;

    inputconditioner dut(.clk(clk),
    			 .noisysignal(pin),
			 .conditioned(conditioned),
			 .positiveedge(rising),
			 .negativeedge(falling));


    // Generate clock (50MHz)
    initial clk=0;
    always #5 clk=!clk;    // 50MHz Clock

    initial begin
        $dumpfile("inputconditioner.vcd");
        $dumpvars;
        // Initialize conditioner by running at 0 for 3 clock cycles
        pin=0; #40

        pin=1; #10
        pin=0; #10
        pin=1; #80
        pin=0; #100
        pin=1; #10
        pin=0; #10
        pin=1; #10
        pin=0; #10
        pin=1; #80
        pin=0;
        #100
        $finish;
    end

    // Your Test Code
    // Be sure to test each of the three conditioner functions:
    // Synchronization, Debouncing, Edge Detection

endmodule

inputconditioner.vcd
$date
	Wed Oct 25 11:52:03 2017
$end
$version
	Icarus Verilog
$end
$timescale
	1s
$end
$scope module testConditioner $end
$var wire 1 ! conditioned $end
$var wire 1 " falling $end
$var wire 1 # rising $end
$var reg 1 $ clk $end
$var reg 1 % pin $end
$scope module dut $end
$var wire 1 & clk $end
$var wire 1 ! conditioned $end
$var wire 1 ' noisysignal $end
$var reg 1 ( negativeedge $end
$var reg 1 ) positiveedge $end
$var reg 1 * prevconditioned $end
$scope module deb $end
$var wire 1 & clk $end
$var wire 1 ' sig $end
$var reg 3 + counter [2:0] $end
$var reg 1 , out $end
$var reg 1 - synchronizer0 $end
$var reg 1 . synchronizer1 $end
$upscope $end
$upscope $end
$upscope $end
$enddefinitions $end
#0
$dumpvars
0.
0-
x,
b0 +
0*
x)
x(
0'
0&
0%
0$
x#
x"
x!
$end
#10
b1 +
0(
0"
1$
1&
#20
0$
0&
#30
b10 +
1$
1&
#40
0$
0&
#50
1-
0,
0!
b0 +
1$
1&
1%
1'
#60
0$
0&
#70
1.
1$
1&
#80
0$
0&
#90
b1 +
1$
1&
#100
0$
0&
#110
b10 +
1$
1&
#120
0$
0&
#130
1,
1!
b0 +
1$
1&
