shiftregister.v
//------------------------------------------------------------------------
// Shift Register
//   Parameterized width (in bits)
//   Shift register can operate in two modes:
//      - serial in, parallel out
//      - parallel in, serial out
//------------------------------------------------------------------------

module shiftregister
#(parameter width = 8)
(
input               clk,                // FPGA Clock
input               peripheralClkEdge,  // Edge indicator
input               parallelLoad,       // 1 = Load shift reg with parallelDataIn
input  [width-1:0]  parallelDataIn,     // Load shift reg in parallel
input               serialDataIn,       // Load shift reg serially
output reg [width-1:0]  parallelDataOut,    // Shift reg data contents
output reg          serialDataOut       // Positive edge synchronized
);

reg [width-1:0]      shiftregistermem;

//wire serialDataOut;

always @(posedge clk) begin
    
	if(parallelLoad ==1) begin  // do thisfor parallel data in

		shiftregistermem <= parallelDataIn;
		serialDataOut <= shiftregistermem[width-1];
	end

	else if(parallelLoad ==0) begin   // We are deciding that parallelLoad will win. This takes priority over serial shift - peripheralClkEdge only matters if parallelLoad = 0.
		if (peripheralClkEdge == 1) begin

			shiftregistermem <= {shiftregistermem[width-2:0], serialDataIn};
		parallelDataOut <= shiftregistermem;

		end


	end



end








endmodule

shiftregister.t.v
//------------------------------------------------------------------------
// Shift Register test bench
//------------------------------------------------------------------------

`include "shiftregister.v"

module testshiftregister();

    reg             clk;
    reg             peripheralClkEdge;
    reg             parallelLoad;
    wire[7:0]       parallelDataOut;
    wire            serialDataOut;
    reg[7:0]        parallelDataIn;
    reg             serialDataIn; 


    // Instantiate with parameter width = 8
    shiftregister #(8) dut(.clk(clk), 
    		           .peripheralClkEdge(peripheralClkEdge),
    		           .parallelLoad(parallelLoad), 
    		           .parallelDataIn(parallelDataIn), 
    		           .serialDataIn(serialDataIn), 
    		           .parallelDataOut(parallelDataOut), 
    		           .serialDataOut(serialDataOut));


    initial clk=0;
    always #10 clk=!clk;    // 50MHz Clock  
    
    initial begin
	
$dumpfile("shiftregister.vcd");
$dumpvars();



// Check Parallel In, Serial Out 
	$display("PIn? | PDataIn | SDataOut");
	parallelLoad =1; parallelDataIn = 8'b00011111; #40
	$display("%b   | %b | %b ", parallelLoad, parallelDataIn, serialDataOut); // expect 0
	parallelLoad =1; parallelDataIn = 8'b00111110; #40
	$display("%b   | %b | %b", parallelLoad, parallelDataIn, serialDataOut); // expect 0
	parallelLoad =1; parallelDataIn = 8'b01111101; #40
	$display("%b   | %b | %b", parallelLoad, parallelDataIn, serialDataOut); // expect 0
	parallelLoad =1; parallelDataIn = 8'b11111010; #40
	$display("%b   | %b | %b", parallelLoad, parallelDataIn, serialDataOut); // expect 1
	parallelLoad =1; parallelDataIn = 8'b11110100; #40
	$display("%b   | %b | %b", parallelLoad, parallelDataIn, serialDataOut); // expect 1

// Check Serial In, Parallel Out
// This is what we'll want to do on the FPGA

	$display("PIn? | SDataIn | PDataOut");
	parallelLoad =0; serialDataIn = 1; peripheralClkEdge = 1; #21
	$display("%b    | 	%b      | %b ", parallelLoad, serialDataIn, parallelDataOut);
	parallelLoad =0; serialDataIn = 1;peripheralClkEdge = 1;  #21
	$display("%b    | 	%b      | %b ", parallelLoad, serialDataIn, parallelDataOut);
	parallelLoad =0; serialDataIn = 0;peripheralClkEdge = 1;  #21
	$display("%b    | 	%b      | %b ", parallelLoad, serialDataIn, parallelDataOut);
	parallelLoad =0; serialDataIn = 0;peripheralClkEdge = 1;  #21
	$display("%b    | 	%b      | %b ", parallelLoad, serialDataIn, parallelDataOut);
	parallelLoad =0; serialDataIn = 0;peripheralClkEdge = 1;  #21
	$display("%b    | 	%b      | %b ", parallelLoad, serialDataIn, parallelDataOut);
	parallelLoad =0; serialDataIn = 1;peripheralClkEdge = 1;  #21
	$display("%b    | 	%b      | %b ", parallelLoad, serialDataIn, parallelDataOut);


	$finish;
    end

endmodule

shiftregister.vcd
$date
	Tue Oct 24 21:53:47 2017
$end
$version
	Icarus Verilog
$end
$timescale
	1s
$end
$scope module testshiftregister $end
$var wire 8 ! parallelDataOut [7:0] $end
$var wire 1 " serialDataOut $end
$var reg 1 # clk $end
$var reg 8 $ parallelDataIn [7:0] $end
$var reg 1 % parallelLoad $end
$var reg 1 & peripheralClkEdge $end
$var reg 1 ' serialDataIn $end
$scope module dut $end
$var wire 1 ( clk $end
$var wire 8 ) parallelDataIn [7:0] $end
$var wire 1 * parallelLoad $end
$var wire 1 + peripheralClkEdge $end
$var wire 1 , serialDataIn $end
$var reg 8 - parallelDataOut [7:0] $end
$var reg 1 . serialDataOut $end
$var reg 8 / shiftregistermem [7:0] $end
$upscope $end
$upscope $end
$enddefinitions $end
#0
$dumpvars
bx /
x.
bx -
x,
x+
1*
b11111 )
0(
x'
x&
1%
b11111 $
0#
x"
bx !
$end
#10
b11111 /
1#
1(
#20
0#
0(
#30
0.
0"
1#
1(
#40
0#
0(
b111110 $
b111110 )
#50
b111110 /
1#
1(
#60
0#
0(
#70
1#
1(
#80
0#
0(
b1111101 $
b1111101 )
#90
b1111101 /
1#
1(
#100
0#
0(
#110
1#
1(
#120
0#
0(
b11111010 $
b11111010 )
#130
b11111010 /
1#
1(
#140
0#
0(
#150
1.
1"
1#
1(
#160
0#
0(
b11110100 $
b11110100 )
#170
b11110100 /
1#
1(
#180
0#
0(
#190
1#
1(
#200
0#
0(
1&
1+
1'
1,
0%
0*
#210
b11110100 -
b11110100 !
b11101001 /
1#
1(
#220
0#
0(
#230
b11101001 -
b11101001 !
b11010011 /
1#
1(
#240
0#
0(
#242
0'
0,
#250
b11010011 -
b11010011 !
b10100110 /
1#
1(
#260
0#
0(
#270
b10100110 -
b10100110 !
b1001100 /
1#
1(
#280
0#
0(
#290
b1001100 -
b1001100 !
b10011000 /
1#
1(
#300
0#
0(
#305
1'
1,
#310
b10011000 -
b10011000 !
b110001 /
1#
1(
