shiftregister.v
//------------------------------------------------------------------------
// Shift Register
//   Parameterized width (in bits)
//   Shift register can operate in two modes:
//      - serial in, parallel out
//      - parallel in, serial out
//------------------------------------------------------------------------

module shiftregister
#(parameter width = 8)
(
input               clk,                // FPGA Clock
input               peripheralClkEdge,  // Edge indicator
input               parallelLoad,       // 1 = Load shift reg with parallelDataIn
input  [width-1:0]  parallelDataIn,     // Load shift reg in parallel
input               serialDataIn,       // Load shift reg serially
output [width-1:0]  parallelDataOut,    // Shift reg data contents
output              serialDataOut       // Positive edge synchronized
);

    reg [width-1:0]      shiftregistermem;
    always @(posedge clk) begin
      if(parallelLoad)
  	     shiftregistermem <= parallelDataIn;
    	else begin
    	   shiftregistermem <= {shiftregistermem[width-2:0],serialDataIn};
    	end
    end

    assign parallelDataOut = shiftregistermem;
    assign serialDataOut   = shiftregistermem[width-1];
endmodule

shiftregister.t.v
`include "shiftregister.v"
//------------------------------------------------------------------------
// Shift Register test bench
//------------------------------------------------------------------------

module testshiftregister();

    reg             clk;
    reg             peripheralClkEdge;
    reg             parallelLoad;
    wire[7:0]       parallelDataOut;
    wire            serialDataOut;
    reg[7:0]        parallelDataIn;
    reg             serialDataIn;

    // Instantiate with parameter width = 8
    shiftregister #(8) dut(.clk(clk),
    		           .peripheralClkEdge(peripheralClkEdge),
    		           .parallelLoad(parallelLoad),
    		           .parallelDataIn(parallelDataIn),
    		           .serialDataIn(serialDataIn),
    		           .parallelDataOut(parallelDataOut),
    		           .serialDataOut(serialDataOut));
    reg dutpassed;

    initial begin
      $dumpfile("shift.vcd");
      $dumpvars(0, testshiftregister);
      //initialize
      dutpassed = 1;
      clk = 0; #5;
    	parallelDataIn = 8'd0;
      parallelLoad   = 1;
      clk = 1; #5;
      clk = 0; #5;
      if(parallelDataOut != 8'd0 || ^parallelDataOut === 1'bx) begin
          $display("initialization failed, parallel");
          dutpassed = 0;
      end
      if(serialDataOut != 0 || serialDataOut === 1'bx) begin
          $display("initialization failed, serial");
          dutpassed = 0;
      end

      //serialLoad some bits
      parallelLoad = 0;
      serialDataIn = 1;
      clk = 1; #5; clk = 0; #5;
      serialDataIn = 1;
      clk = 1; #5; clk = 0; #5;
      serialDataIn = 0;
      clk = 1; #5; clk = 0; #5;
      serialDataIn = 0;
      clk = 1; #5; clk = 0; #5;
      serialDataIn = 1;
      clk = 1; #5; clk = 0; #5;
      serialDataIn = 0;
      clk = 1; #5; clk = 0; #5;
      serialDataIn = 1;
      clk = 1; #5; clk = 0; #5;
      serialDataIn = 0;
      clk = 1; #5; clk = 0; #5;
      if(parallelDataOut != 8'b11001010 || ^parallelDataOut === 1'bx) begin
          $display("Serial in failed, parallel");
          dutpassed = 0;
      end
      if(serialDataOut != 1 || serialDataOut === 1'bx) begin
          $display("Serial in failed, serial");
          dutpassed = 0;
      end

      //parallelLoad some bits
      parallelLoad = 1;
      parallelDataIn = 8'b01010011;
      clk = 1; #5; clk = 0; #5;
      if(parallelDataOut != 8'b01010011 || ^parallelDataOut === 1'bx) begin
          $display("Parallel in failed, parallel");
          dutpassed = 0;
      end
      if(serialDataOut != 0 || serialDataOut === 1'bx) begin
          $display("Parallel in failed, serial");
          dutpassed = 0;
      end

      //parallel and serial at the same time
      parallelLoad = 1;
      serialDataIn = 0;
      parallelDataIn = 8'b11111111;
      clk = 1; #5; clk = 0; #5;
      if(parallelDataOut != 8'b11111111 || ^parallelDataOut === 1'bx) begin
          $display("Same time in failed, parallel");
          dutpassed = 0;
      end
      if(serialDataOut != 1 || serialDataOut === 1'bx) begin
          $display("Same time in failed, serial");
          dutpassed = 0;
      end

      if(dutpassed) begin
          $display("DUT passed!");
      end
      $finish();
    end
endmodule

shift.vcd
$date
	Tue Oct 24 11:28:11 2017
$end
$version
	Icarus Verilog
$end
$timescale
	1s
$end
$scope module testshiftregister $end
$var wire 1 ! serialDataOut $end
$var wire 8 " parallelDataOut [7:0] $end
$var reg 1 # clk $end
$var reg 1 $ dutpassed $end
$var reg 8 % parallelDataIn [7:0] $end
$var reg 1 & parallelLoad $end
$var reg 1 ' peripheralClkEdge $end
$var reg 1 ( serialDataIn $end
$scope module dut $end
$var wire 1 # clk $end
$var wire 8 ) parallelDataIn [7:0] $end
$var wire 8 * parallelDataOut [7:0] $end
$var wire 1 & parallelLoad $end
$var wire 1 ' peripheralClkEdge $end
$var wire 1 ( serialDataIn $end
$var wire 1 ! serialDataOut $end
$var reg 8 + shiftregistermem [7:0] $end
$upscope $end
$upscope $end
$enddefinitions $end
#0
$dumpvars
bx +
bx *
bx )
x(
x'
x&
bx %
1$
0#
bx "
x!
$end
#5
0!
b0 "
b0 *
b0 +
1#
1&
b0 %
b0 )
#10
0#
#15
b1 "
b1 *
b1 +
1#
1(
0&
#20
0#
#25
b11 "
b11 *
b11 +
1#
#30
0#
#35
b110 "
b110 *
b110 +
1#
0(
#40
0#
#45
b1100 "
b1100 *
b1100 +
1#
#50
0#
#55
b11001 "
b11001 *
b11001 +
1#
1(
#60
0#
#65
b110010 "
b110010 *
b110010 +
1#
0(
#70
0#
#75
b1100101 "
b1100101 *
b1100101 +
1#
1(
#80
0#
#85
1!
b11001010 "
b11001010 *
b11001010 +
1#
0(
#90
0#
#95
0!
b1010011 "
b1010011 *
b1010011 +
1#
b1010011 %
b1010011 )
1&
#100
0#
#105
1!
b11111111 "
b11111111 *
b11111111 +
1#
b11111111 %
b11111111 )
