shiftregister.t.v
//------------------------------------------------------------------------
// Shift Register test bench
//------------------------------------------------------------------------

`include "shiftregister.v"

module testshiftregister();

    reg             clk;
    reg             peripheralClkEdge;
    reg             parallelLoad;
    wire[7:0]       parallelDataOut;
    wire            serialDataOut;
    reg[7:0]        parallelDataIn;
    reg             serialDataIn; 

    // Instantiate with parameter width = 8
    shiftregister #(8) dut(.clk(clk), 
    		           .peripheralClkEdge(peripheralClkEdge),
    		           .parallelLoad(parallelLoad), 
    		           .parallelDataIn(parallelDataIn), 
    		           .serialDataIn(serialDataIn), 
    		           .parallelDataOut(parallelDataOut), 
    		           .serialDataOut(serialDataOut));


    initial clk=0;
    always #10 clk=!clk;    // 50MHz Clock  
    
    initial begin
	
$dumpfile("shiftregister.vcd");
$dumpvars();


	$display("PIn? | PDataIn | SDataOut");
	parallelLoad =1; parallelDataIn = 8'b00011111; #20
	$display("%b | %b | %b ", parallelLoad, parallelDataIn, serialDataOut);
	parallelLoad =1; parallelDataIn = 8'b00111101; #20
	$display("%b | %b | %b", parallelLoad, parallelDataIn, serialDataOut);
		parallelLoad =1; parallelDataIn = 8'b10011110; #20
	$display("%b | %b | %b", parallelLoad, parallelDataIn, serialDataOut);



	$display("PIn? | PClock| SDataIn | PDataOut");
	parallelLoad =0; peripheralClkEdge = 1; serialDataIn = 1; #20
	$display("%b    |    %b | 	%b 	| %b ", parallelLoad, peripheralClkEdge, serialDataIn, parallelDataOut);
	parallelLoad =0; peripheralClkEdge = 0; serialDataIn = 1; #20
	$display("%b    |    %b | 	%b 	| %b ", parallelLoad, peripheralClkEdge, serialDataIn, parallelDataOut);
	parallelLoad =0; peripheralClkEdge = 1; serialDataIn = 0; #20
	$display("%b    |    %b | 	%b	| %b ", parallelLoad, peripheralClkEdge, serialDataIn, parallelDataOut);
	parallelLoad =0; peripheralClkEdge = 0; serialDataIn = 0; #20
	$display("%b    |    %b | 	%b	| %b ", parallelLoad, peripheralClkEdge, serialDataIn, parallelDataOut);
	parallelLoad =0; peripheralClkEdge =1; serialDataIn = 0; #20
	$display("%b    |    %b | 	%b	| %b ", parallelLoad, peripheralClkEdge, serialDataIn, parallelDataOut);


	$finish;
    end

endmodule

shiftregister.v
//------------------------------------------------------------------------
// Shift Register
//   Parameterized width (in bits)
//   Shift register can operate in two modes:
//      - serial in, parallel out
//      - parallel in, serial out
//------------------------------------------------------------------------

module shiftregister
#(parameter width = 8)
(
input               clk,                // FPGA Clock
input               peripheralClkEdge,  // Edge indicator
input               parallelLoad,       // 1 = Load shift reg with parallelDataIn
input  [width-1:0]  parallelDataIn,     // Load shift reg in parallel
input               serialDataIn,       // Load shift reg serially
output reg [width-1:0]  parallelDataOut,    // Shift reg data contents
output reg          serialDataOut       // Positive edge synchronized
);

reg [width-1:0]      shiftregistermem;

//wire serialDataOut;

always @(posedge clk) begin
    
	if(parallelLoad ==1) begin  // do thisfor parallel data in

		shiftregistermem <= parallelDataIn;
		serialDataOut <= shiftregistermem[width-1];
		parallelDataOut <= shiftregistermem;

	end

	if(parallelLoad ==0) begin   // We are deciding that parallelLoad will win. This takes priority over serial shift - peripheralClkEdge only matters if parallelLoad = 0.
		if (peripheralClkEdge == 1) begin

			shiftregistermem[1] <= shiftregistermem[0];
			shiftregistermem[2] <= shiftregistermem[1];
			shiftregistermem[3] <= shiftregistermem[2];
			shiftregistermem[4] <= shiftregistermem[3];
			shiftregistermem[5] <= shiftregistermem[4];
			shiftregistermem[6] <= shiftregistermem[5];
			shiftregistermem[7] <= shiftregistermem[6];
			shiftregistermem[0] <= serialDataIn;
			//shiftregistermem <= {{shiftregistermem[width-2:0]}, {serialDataIn}};
		end
		parallelDataOut <= shiftregistermem;

	end

end

endmodule

// general thoughts: make a loop that happens width # of times, 
// and then use the idea behind the behavioral flip flop below  
// so that you can pass things along as needed. 

// from the assignment: 
// " Each of these four behaviors can be implemented in one or two lines of behavioral Verilog. 
// You may want to look at Verilog's {} concatenate syntax for implementing the serial behavior. "



module flipflop
(
output reg  q,
input       d,
input       wrenable,
input       clk
);
    always @(posedge clk) begin
        if(wrenable) begin
            q = d;
        end
    end
endmodule

shiftregister.vcd
$date
	Tue Oct 24 18:10:09 2017
$end
$version
	Icarus Verilog
$end
$timescale
	1s
$end
$scope module flipflop $end
$var wire 1 ! clk $end
$var wire 1 " d $end
$var wire 1 # wrenable $end
$var reg 1 $ q $end
$upscope $end
$scope module testshiftregister $end
$var wire 8 % parallelDataOut [7:0] $end
$var wire 1 & serialDataOut $end
$var reg 1 ' clk $end
$var reg 8 ( parallelDataIn [7:0] $end
$var reg 1 ) parallelLoad $end
$var reg 1 * peripheralClkEdge $end
$var reg 1 + serialDataIn $end
$scope module dut $end
$var wire 1 , clk $end
$var wire 8 - parallelDataIn [7:0] $end
$var wire 1 . parallelLoad $end
$var wire 1 / peripheralClkEdge $end
$var wire 1 0 serialDataIn $end
$var reg 8 1 parallelDataOut [7:0] $end
$var reg 1 2 serialDataOut $end
$var reg 8 3 shiftregistermem [7:0] $end
$upscope $end
$upscope $end
$enddefinitions $end
#0
$dumpvars
bx 3
x2
bx 1
x0
x/
1.
b11111 -
0,
x+
x*
1)
b11111 (
0'
x&
bx %
x$
z#
z"
z!
$end
#10
b11111 3
1'
1,
#20
0'
0,
b111101 (
b111101 -
#30
b11111 1
b11111 %
02
0&
b111101 3
1'
1,
#40
0'
0,
b10011110 (
b10011110 -
#50
b111101 1
b111101 %
b10011110 3
1'
1,
#60
0'
0,
1+
10
1*
1/
0)
0.
#70
b10011110 1
b10011110 %
b111101 3
1'
1,
#80
0'
0,
0*
0/
#90
b111101 1
b111101 %
1'
1,
#100
0'
0,
0+
00
1*
1/
#110
b1111010 3
1'
1,
#120
0'
0,
0*
0/
#130
b1111010 1
b1111010 %
1'
1,
#140
0'
0,
1*
1/
#150
b11110100 3
1'
1,
