shiftregister.v
//------------------------------------------------------------------------
// Shift Register
//   Parameterized width (in bits)
//   Shift register can operate in two modes:
//      - serial in, parallel out
//      - parallel in, serial out
//------------------------------------------------------------------------

module shiftregister
#(parameter width = 8)
(
input               clk,                // FPGA Clock
input               peripheralClkEdge,  // Edge indicator
input               parallelLoad,       // 1 = Load shift reg with parallelDataIn
input  [width-1:0]  parallelDataIn,     // Load shift reg in parallel
input               serialDataIn,       // Load shift reg serially
output [width-1:0]  parallelDataOut,    // Shift reg data contents
output              serialDataOut       // Positive edge synchronized
);

    reg [width-1:0]      data;

    always @(posedge clk) begin
        if (parallelLoad) begin
            data <= parallelDataIn;
        end
        else if (peripheralClkEdge) begin
        	data <= {data[width - 2:0], serialDataIn};
        end
        
    end
    assign serialDataOut = data[width - 1];
    assign parallelDataOut = data;


endmodule

shiftregister.t.v
//------------------------------------------------------------------------
// Shift Register test bench
//------------------------------------------------------------------------
`include "shiftregister.v"

module testshiftregister();

    reg             clk;
    reg             peripheralClkEdge;
    reg             parallelLoad;
    wire[7:0]       parallelDataOut;
    wire            serialDataOut;
    reg[7:0]        parallelDataIn;
    reg             serialDataIn;

    // Instantiate with parameter width = 8
    shiftregister #(8) dut(.clk(clk),
    		           .peripheralClkEdge(peripheralClkEdge),
    		           .parallelLoad(parallelLoad),
    		           .parallelDataIn(parallelDataIn),
    		           .serialDataIn(serialDataIn),
    		           .parallelDataOut(parallelDataOut),
    		           .serialDataOut(serialDataOut));
    
    initial clk = 0;
    always #5 clk=!clk; 
    initial begin
        //$dumpfile("shiftregister.vcd");
        //$dumpvars;


        // Test parallel loads
    	parallelLoad = 1;
        parallelDataIn = 8'b00000000;
        #20;
        if (parallelDataOut == 8'b00000000) begin
            $display("Test Case 1 Passed");
        end
        else begin
            $display("Test Case 1 Failed!");
        end

        parallelDataIn = 8'b00001111;
        #20;
        if (parallelDataOut == 8'b00001111) begin
            $display("Test Case 2 Passed");
        end
        else begin
            $display("Test Case 2 Failed!");
        end

        parallelDataIn = 8'b11111111;
        #20;
        if (parallelDataOut == 8'b11111111) begin
            $display("Test Case 3 Passed");
        end
        else begin
            $display("Test Case 3 Failed!");
        end

        parallelLoad = 0;
        parallelDataIn = 8'b00000000;
        #20;
        if (parallelDataOut == 8'b00000000) begin
            $display("Test Case 4 Failed!");
        end
        else begin
            $display("Test Case 4 Passed");
        end
        $finish;

        // Manual clock
        parallelLoad = 0;
        serialDataIn = 1;
        peripheralClkEdge = 1;
        
        clk = 0; clk = 1; clk = 0;
        if (parallelDataOut == 8'b00000001) begin
            $display("passed ----");
        end
        else begin
            $display("failed -----");
            $display("%8b", parallelDataOut);
        end
        serialDataIn = 0;
        
        clk = 1; clk = 0;
        if (parallelDataOut == 8'b00000010) begin
            $display("passed ----");
        end
        else begin
            $display("failed -----");
            $display("%8b", parallelDataOut);
        end
        
        /*if (parallelDataOut == 8'b00000010) begin
            $display("passed ----");
        end
        else begin
            $display("failed -----");
            $display("%8b", parallelDataOut);
        end*/

        //peripheralClkEdge = 1;

        /*serialDataIn = 1; #10
        if (serialDataOut == 0) begin
            $display("Passed Test Case 1");
        end
        else begin
            $display("Failed Test Case 1");
            $display(serialDataOut);
            $display("%8b", parallelDataOut);
        end
        if (parallelDataOut == 1) begin
            $display("Failed Test Case 2");
        end
        else begin
            $display("Passed Test Case 2");
        end
        #30
        if (serialDataOut != 0) begin
            $display("Failed Test Case 3");
        end
        if (parallelDataOut != 8) begin
            $display("Failed Test Case 4");
        end*/
        
        /*if (parallelLoad == 0) begin
            $display("Failed!");
        end
        serialDataIn = 0; #10
        serialDataIn = 1; #10
        serialDataIn = 1; #10
        serialDataIn = 1; 
        #100*/

        //$finish;
    end

endmodule

shiftregister.vcd
$date
	Wed Oct 25 20:27:31 2017
$end
$version
	Icarus Verilog
$end
$timescale
	1s
$end
$scope module testshiftregister $end
$var wire 8 ! parallelDataOut [7:0] $end
$var wire 1 " serialDataOut $end
$var reg 1 # clk $end
$var reg 8 $ parallelDataIn [7:0] $end
$var reg 1 % parallelLoad $end
$var reg 1 & peripheralClkEdge $end
$var reg 1 ' serialDataIn $end
$scope module dut $end
$var wire 1 ( clk $end
$var wire 8 ) parallelDataIn [7:0] $end
$var wire 8 * parallelDataOut [7:0] $end
$var wire 1 + parallelLoad $end
$var wire 1 , peripheralClkEdge $end
$var wire 1 - serialDataIn $end
$var wire 1 " serialDataOut $end
$var reg 8 . data [7:0] $end
$upscope $end
$upscope $end
$enddefinitions $end
#0
$dumpvars
b0 .
x-
0,
1+
b0 *
b0 )
1(
x'
0&
1%
b0 $
1#
0"
b0 !
$end
#10
0#
0(
#20
b1111 .
b1111 !
b1111 *
1#
1(
b1111 $
b1111 )
#30
0#
0(
#40
1"
b11111111 .
b11111111 !
b11111111 *
1#
1(
b11111111 $
b11111111 )
#50
0#
0(
#60
1#
1(
b0 $
b0 )
0%
0+
#70
0#
0(
#90
0"
b0 .
b0 !
b0 *
1#
1(
1%
1+
#100
0#
0(
#110
b1 .
b1 !
b1 *
1#
1(
1&
1,
1'
1-
0%
0+
#115
0#
0(
#120
b11 .
b11 !
b11 *
1#
1(
#125
0#
0(
#130
b111 .
b111 !
b111 *
1#
1(
#135
0#
0(
#140
b1110 .
b1110 !
b1110 *
1#
1(
0'
0-
